README.md
setup.py
toISOString/__init__.py
toISOString/toISOString.py
toISOString.egg-info/PKG-INFO
toISOString.egg-info/SOURCES.txt
toISOString.egg-info/dependency_links.txt
toISOString.egg-info/requires.txt
toISOString.egg-info/top_level.txt