Metadata-Version: 2.1
Name: toISOString
Version: 0.0.4
Summary: UNKNOWN
Home-page: https://github.com/kaleocheng/toISOString
Author: Kaleo Cheng
Author-email: kaleocheng@gmail.com
License: UNKNOWN
Platform: UNKNOWN
Classifier: Programming Language :: Python :: 3
Classifier: License :: OSI Approved :: MIT License
Classifier: Operating System :: OS Independent
